{
  "menu": [
    {
      "titleKey": "category",
      "items": [
        { "labelKey": "women", "href": "#" },
        { "labelKey": "men", "href": "#" },
        { "labelKey": "unisex", "href": "#" },
        { "labelKey": "kids", "href": "#" }
      ]
    },
    {
      "titleKey": "brands",
      "items": [
        { "labelKey": "polaroid", "href": "#" },
        { "labelKey": "rayban", "href": "#" },
        { "labelKey": "emporio_armani", "href": "#" },
        { "labelKey": "gucci", "href": "#" }
      ]
    },
    {
      "titleKey": "material",
      "items": [
        { "labelKey": "metal", "href": "#" },
        { "labelKey": "plastic", "href": "#" },
        { "labelKey": "titanium", "href": "#" },
        { "labelKey": "nylon", "href": "#" }
      ]
    },
    {
      "titleKey": "accessories",
      "items": [
        { "labelKey": "chains", "href": "#" },
        { "labelKey": "cases", "href": "#" },
        { "labelKey": "napkins", "href": "#" },
        { "labelKey": "care", "href": "#" }
      ]
    }
  ],
  "shapes": [
    {
      "labelKey": "aviator",
      "href": "#",
      "image": "/images/products/glasses/glasses_4.png"
    },
    {
      "labelKey": "square",
      "href": "#",
      "image": "/images/products/glasses/glasses_5.png"
    },
    {
      "labelKey": "round",
      "href": "#",
      "image": "/images/products/glasses/glasses_6.png"
    },
    {
      "labelKey": "cat_eye",
      "href": "#",
      "image": "/images/products/glasses/glasses_7.png"
    }
  ]
}
